{
  "generated_at": "2026-04-07T02:29:11.127774Z",
  "total": 633,
  "countries": [
    {
      "code": "RU",
      "flag": "🇷🇺",
      "count": 331
    },
    {
      "code": "AL",
      "flag": "🇦🇱",
      "count": 2
    },
    {
      "code": "AT",
      "flag": "🇦🇹",
      "count": 1
    },
    {
      "code": "CA",
      "flag": "🇨🇦",
      "count": 1
    },
    {
      "code": "CH",
      "flag": "🇨🇭",
      "count": 10
    },
    {
      "code": "CZ",
      "flag": "🇨🇿",
      "count": 1
    },
    {
      "code": "DE",
      "flag": "🇩🇪",
      "count": 199
    },
    {
      "code": "EE",
      "flag": "🇪🇪",
      "count": 2
    },
    {
      "code": "FI",
      "flag": "🇫🇮",
      "count": 3
    },
    {
      "code": "FR",
      "flag": "🇫🇷",
      "count": 8
    },
    {
      "code": "GB",
      "flag": "🇬🇧",
      "count": 3
    },
    {
      "code": "HU",
      "flag": "🇭🇺",
      "count": 2
    },
    {
      "code": "IT",
      "flag": "🇮🇹",
      "count": 1
    },
    {
      "code": "LT",
      "flag": "🇱🇹",
      "count": 4
    },
    {
      "code": "LV",
      "flag": "🇱🇻",
      "count": 2
    },
    {
      "code": "NL",
      "flag": "🇳🇱",
      "count": 24
    },
    {
      "code": "NO",
      "flag": "🇳🇴",
      "count": 2
    },
    {
      "code": "PH",
      "flag": "🇵🇭",
      "count": 1
    },
    {
      "code": "PL",
      "flag": "🇵🇱",
      "count": 3
    },
    {
      "code": "SE",
      "flag": "🇸🇪",
      "count": 8
    },
    {
      "code": "SK",
      "flag": "🇸🇰",
      "count": 1
    },
    {
      "code": "US",
      "flag": "🇺🇸",
      "count": 3
    },
    {
      "code": "XX",
      "flag": "🇽🇽",
      "count": 21
    }
  ]
}