{
  "generated_at": "2026-04-10T01:40:09.874313Z",
  "total": 542,
  "countries": [
    {
      "code": "RU",
      "flag": "🇷🇺",
      "count": 67
    },
    {
      "code": "AM",
      "flag": "🇦🇲",
      "count": 1
    },
    {
      "code": "CA",
      "flag": "🇨🇦",
      "count": 1
    },
    {
      "code": "CZ",
      "flag": "🇨🇿",
      "count": 5
    },
    {
      "code": "DE",
      "flag": "🇩🇪",
      "count": 185
    },
    {
      "code": "ES",
      "flag": "🇪🇸",
      "count": 2
    },
    {
      "code": "FI",
      "flag": "🇫🇮",
      "count": 10
    },
    {
      "code": "FR",
      "flag": "🇫🇷",
      "count": 21
    },
    {
      "code": "GB",
      "flag": "🇬🇧",
      "count": 4
    },
    {
      "code": "HK",
      "flag": "🇭🇰",
      "count": 1
    },
    {
      "code": "HU",
      "flag": "🇭🇺",
      "count": 108
    },
    {
      "code": "JP",
      "flag": "🇯🇵",
      "count": 3
    },
    {
      "code": "LT",
      "flag": "🇱🇹",
      "count": 37
    },
    {
      "code": "NL",
      "flag": "🇳🇱",
      "count": 34
    },
    {
      "code": "PL",
      "flag": "🇵🇱",
      "count": 14
    },
    {
      "code": "SE",
      "flag": "🇸🇪",
      "count": 5
    },
    {
      "code": "US",
      "flag": "🇺🇸",
      "count": 10
    },
    {
      "code": "XX",
      "flag": "🇽🇽",
      "count": 34
    }
  ]
}