{
  "generated_at": "2026-04-09T00:21:28.373126Z",
  "total": 573,
  "countries": [
    {
      "code": "RU",
      "flag": "🇷🇺",
      "count": 121
    },
    {
      "code": "AE",
      "flag": "🇦🇪",
      "count": 1
    },
    {
      "code": "AL",
      "flag": "🇦🇱",
      "count": 1
    },
    {
      "code": "AM",
      "flag": "🇦🇲",
      "count": 1
    },
    {
      "code": "CA",
      "flag": "🇨🇦",
      "count": 7
    },
    {
      "code": "CH",
      "flag": "🇨🇭",
      "count": 4
    },
    {
      "code": "CZ",
      "flag": "🇨🇿",
      "count": 5
    },
    {
      "code": "DE",
      "flag": "🇩🇪",
      "count": 118
    },
    {
      "code": "EE",
      "flag": "🇪🇪",
      "count": 1
    },
    {
      "code": "ES",
      "flag": "🇪🇸",
      "count": 2
    },
    {
      "code": "FI",
      "flag": "🇫🇮",
      "count": 13
    },
    {
      "code": "FR",
      "flag": "🇫🇷",
      "count": 47
    },
    {
      "code": "GB",
      "flag": "🇬🇧",
      "count": 7
    },
    {
      "code": "HU",
      "flag": "🇭🇺",
      "count": 44
    },
    {
      "code": "KZ",
      "flag": "🇰🇿",
      "count": 1
    },
    {
      "code": "LT",
      "flag": "🇱🇹",
      "count": 31
    },
    {
      "code": "LV",
      "flag": "🇱🇻",
      "count": 2
    },
    {
      "code": "NL",
      "flag": "🇳🇱",
      "count": 27
    },
    {
      "code": "NO",
      "flag": "🇳🇴",
      "count": 1
    },
    {
      "code": "PL",
      "flag": "🇵🇱",
      "count": 54
    },
    {
      "code": "SE",
      "flag": "🇸🇪",
      "count": 2
    },
    {
      "code": "SK",
      "flag": "🇸🇰",
      "count": 1
    },
    {
      "code": "TR",
      "flag": "🇹🇷",
      "count": 12
    },
    {
      "code": "UA",
      "flag": "🇺🇦",
      "count": 1
    },
    {
      "code": "US",
      "flag": "🇺🇸",
      "count": 16
    },
    {
      "code": "VN",
      "flag": "🇻🇳",
      "count": 6
    },
    {
      "code": "XX",
      "flag": "🇽🇽",
      "count": 47
    }
  ]
}