{
  "generated_at": "2026-03-19T21:54:38.138037Z",
  "total": 899,
  "countries": [
    {
      "code": "RU",
      "flag": "🇷🇺",
      "count": 248
    },
    {
      "code": "BG",
      "flag": "🇧🇬",
      "count": 7
    },
    {
      "code": "CY",
      "flag": "🇨🇾",
      "count": 4
    },
    {
      "code": "DE",
      "flag": "🇩🇪",
      "count": 191
    },
    {
      "code": "EE",
      "flag": "🇪🇪",
      "count": 7
    },
    {
      "code": "FI",
      "flag": "🇫🇮",
      "count": 21
    },
    {
      "code": "FR",
      "flag": "🇫🇷",
      "count": 22
    },
    {
      "code": "GB",
      "flag": "🇬🇧",
      "count": 39
    },
    {
      "code": "HK",
      "flag": "🇭🇰",
      "count": 1
    },
    {
      "code": "HU",
      "flag": "🇭🇺",
      "count": 1
    },
    {
      "code": "IS",
      "flag": "🇮🇸",
      "count": 3
    },
    {
      "code": "KR",
      "flag": "🇰🇷",
      "count": 40
    },
    {
      "code": "KZ",
      "flag": "🇰🇿",
      "count": 3
    },
    {
      "code": "LT",
      "flag": "🇱🇹",
      "count": 4
    },
    {
      "code": "LV",
      "flag": "🇱🇻",
      "count": 9
    },
    {
      "code": "NL",
      "flag": "🇳🇱",
      "count": 88
    },
    {
      "code": "NO",
      "flag": "🇳🇴",
      "count": 1
    },
    {
      "code": "PL",
      "flag": "🇵🇱",
      "count": 43
    },
    {
      "code": "RS",
      "flag": "🇷🇸",
      "count": 3
    },
    {
      "code": "SE",
      "flag": "🇸🇪",
      "count": 2
    },
    {
      "code": "US",
      "flag": "🇺🇸",
      "count": 39
    },
    {
      "code": "XX",
      "flag": "🇽🇽",
      "count": 123
    }
  ]
}