{
  "generated_at": "2026-03-19T15:20:23.543845Z",
  "total": 797,
  "countries": [
    {
      "code": "RU",
      "flag": "🇷🇺",
      "count": 163
    },
    {
      "code": "BE",
      "flag": "🇧🇪",
      "count": 6
    },
    {
      "code": "BG",
      "flag": "🇧🇬",
      "count": 3
    },
    {
      "code": "CH",
      "flag": "🇨🇭",
      "count": 7
    },
    {
      "code": "CY",
      "flag": "🇨🇾",
      "count": 2
    },
    {
      "code": "CZ",
      "flag": "🇨🇿",
      "count": 3
    },
    {
      "code": "DE",
      "flag": "🇩🇪",
      "count": 196
    },
    {
      "code": "EE",
      "flag": "🇪🇪",
      "count": 6
    },
    {
      "code": "FI",
      "flag": "🇫🇮",
      "count": 41
    },
    {
      "code": "FR",
      "flag": "🇫🇷",
      "count": 9
    },
    {
      "code": "GB",
      "flag": "🇬🇧",
      "count": 26
    },
    {
      "code": "HK",
      "flag": "🇭🇰",
      "count": 2
    },
    {
      "code": "HU",
      "flag": "🇭🇺",
      "count": 7
    },
    {
      "code": "IN",
      "flag": "🇮🇳",
      "count": 1
    },
    {
      "code": "KR",
      "flag": "🇰🇷",
      "count": 24
    },
    {
      "code": "KZ",
      "flag": "🇰🇿",
      "count": 3
    },
    {
      "code": "LT",
      "flag": "🇱🇹",
      "count": 2
    },
    {
      "code": "LU",
      "flag": "🇱🇺",
      "count": 11
    },
    {
      "code": "LV",
      "flag": "🇱🇻",
      "count": 5
    },
    {
      "code": "MD",
      "flag": "🇲🇩",
      "count": 6
    },
    {
      "code": "NL",
      "flag": "🇳🇱",
      "count": 99
    },
    {
      "code": "NO",
      "flag": "🇳🇴",
      "count": 1
    },
    {
      "code": "PL",
      "flag": "🇵🇱",
      "count": 37
    },
    {
      "code": "RO",
      "flag": "🇷🇴",
      "count": 13
    },
    {
      "code": "SE",
      "flag": "🇸🇪",
      "count": 14
    },
    {
      "code": "SI",
      "flag": "🇸🇮",
      "count": 6
    },
    {
      "code": "US",
      "flag": "🇺🇸",
      "count": 32
    },
    {
      "code": "XX",
      "flag": "🇽🇽",
      "count": 72
    }
  ]
}