{
  "generated_at": "2026-04-01T17:37:52.109661Z",
  "total": 270,
  "countries": [
    {
      "code": "RU",
      "flag": "🇷🇺",
      "count": 159
    },
    {
      "code": "DE",
      "flag": "🇩🇪",
      "count": 40
    },
    {
      "code": "EE",
      "flag": "🇪🇪",
      "count": 4
    },
    {
      "code": "ES",
      "flag": "🇪🇸",
      "count": 1
    },
    {
      "code": "FI",
      "flag": "🇫🇮",
      "count": 2
    },
    {
      "code": "GB",
      "flag": "🇬🇧",
      "count": 1
    },
    {
      "code": "ID",
      "flag": "🇮🇩",
      "count": 1
    },
    {
      "code": "IT",
      "flag": "🇮🇹",
      "count": 7
    },
    {
      "code": "LT",
      "flag": "🇱🇹",
      "count": 31
    },
    {
      "code": "NL",
      "flag": "🇳🇱",
      "count": 11
    },
    {
      "code": "PL",
      "flag": "🇵🇱",
      "count": 8
    },
    {
      "code": "XX",
      "flag": "🇽🇽",
      "count": 5
    }
  ]
}