{
  "generated_at": "2026-03-30T10:01:02.120093Z",
  "total": 299,
  "countries": [
    {
      "code": "RU",
      "flag": "🇷🇺",
      "count": 51
    },
    {
      "code": "BG",
      "flag": "🇧🇬",
      "count": 3
    },
    {
      "code": "CA",
      "flag": "🇨🇦",
      "count": 1
    },
    {
      "code": "CZ",
      "flag": "🇨🇿",
      "count": 1
    },
    {
      "code": "DE",
      "flag": "🇩🇪",
      "count": 35
    },
    {
      "code": "EE",
      "flag": "🇪🇪",
      "count": 3
    },
    {
      "code": "ES",
      "flag": "🇪🇸",
      "count": 26
    },
    {
      "code": "FI",
      "flag": "🇫🇮",
      "count": 1
    },
    {
      "code": "FR",
      "flag": "🇫🇷",
      "count": 3
    },
    {
      "code": "GB",
      "flag": "🇬🇧",
      "count": 1
    },
    {
      "code": "HK",
      "flag": "🇭🇰",
      "count": 1
    },
    {
      "code": "HU",
      "flag": "🇭🇺",
      "count": 4
    },
    {
      "code": "ID",
      "flag": "🇮🇩",
      "count": 1
    },
    {
      "code": "IT",
      "flag": "🇮🇹",
      "count": 16
    },
    {
      "code": "LV",
      "flag": "🇱🇻",
      "count": 1
    },
    {
      "code": "NL",
      "flag": "🇳🇱",
      "count": 60
    },
    {
      "code": "PL",
      "flag": "🇵🇱",
      "count": 6
    },
    {
      "code": "SE",
      "flag": "🇸🇪",
      "count": 16
    },
    {
      "code": "UN",
      "flag": "🇺🇳",
      "count": 1
    },
    {
      "code": "US",
      "flag": "🇺🇸",
      "count": 17
    },
    {
      "code": "XX",
      "flag": "🇽🇽",
      "count": 51
    }
  ]
}