{
  "generated_at": "2026-04-02T17:08:44.370546Z",
  "total": 727,
  "countries": [
    {
      "code": "RU",
      "flag": "🇷🇺",
      "count": 262
    },
    {
      "code": "AL",
      "flag": "🇦🇱",
      "count": 10
    },
    {
      "code": "CH",
      "flag": "🇨🇭",
      "count": 22
    },
    {
      "code": "DE",
      "flag": "🇩🇪",
      "count": 111
    },
    {
      "code": "EE",
      "flag": "🇪🇪",
      "count": 6
    },
    {
      "code": "ES",
      "flag": "🇪🇸",
      "count": 19
    },
    {
      "code": "FI",
      "flag": "🇫🇮",
      "count": 7
    },
    {
      "code": "FR",
      "flag": "🇫🇷",
      "count": 29
    },
    {
      "code": "GB",
      "flag": "🇬🇧",
      "count": 2
    },
    {
      "code": "HU",
      "flag": "🇭🇺",
      "count": 53
    },
    {
      "code": "ID",
      "flag": "🇮🇩",
      "count": 1
    },
    {
      "code": "IT",
      "flag": "🇮🇹",
      "count": 16
    },
    {
      "code": "JP",
      "flag": "🇯🇵",
      "count": 1
    },
    {
      "code": "LT",
      "flag": "🇱🇹",
      "count": 32
    },
    {
      "code": "LV",
      "flag": "🇱🇻",
      "count": 1
    },
    {
      "code": "NL",
      "flag": "🇳🇱",
      "count": 44
    },
    {
      "code": "PL",
      "flag": "🇵🇱",
      "count": 7
    },
    {
      "code": "SE",
      "flag": "🇸🇪",
      "count": 46
    },
    {
      "code": "TR",
      "flag": "🇹🇷",
      "count": 2
    },
    {
      "code": "UN",
      "flag": "🇺🇳",
      "count": 3
    },
    {
      "code": "US",
      "flag": "🇺🇸",
      "count": 34
    },
    {
      "code": "XX",
      "flag": "🇽🇽",
      "count": 19
    }
  ]
}