{
  "generated_at": "2026-04-02T21:45:24.500660Z",
  "total": 486,
  "countries": [
    {
      "code": "RU",
      "flag": "🇷🇺",
      "count": 260
    },
    {
      "code": "CH",
      "flag": "🇨🇭",
      "count": 10
    },
    {
      "code": "DE",
      "flag": "🇩🇪",
      "count": 61
    },
    {
      "code": "EE",
      "flag": "🇪🇪",
      "count": 2
    },
    {
      "code": "ES",
      "flag": "🇪🇸",
      "count": 13
    },
    {
      "code": "FI",
      "flag": "🇫🇮",
      "count": 2
    },
    {
      "code": "FR",
      "flag": "🇫🇷",
      "count": 25
    },
    {
      "code": "GB",
      "flag": "🇬🇧",
      "count": 1
    },
    {
      "code": "HU",
      "flag": "🇭🇺",
      "count": 33
    },
    {
      "code": "ID",
      "flag": "🇮🇩",
      "count": 1
    },
    {
      "code": "LT",
      "flag": "🇱🇹",
      "count": 16
    },
    {
      "code": "LV",
      "flag": "🇱🇻",
      "count": 1
    },
    {
      "code": "NL",
      "flag": "🇳🇱",
      "count": 31
    },
    {
      "code": "PL",
      "flag": "🇵🇱",
      "count": 6
    },
    {
      "code": "SE",
      "flag": "🇸🇪",
      "count": 1
    },
    {
      "code": "TR",
      "flag": "🇹🇷",
      "count": 1
    },
    {
      "code": "UN",
      "flag": "🇺🇳",
      "count": 1
    },
    {
      "code": "US",
      "flag": "🇺🇸",
      "count": 5
    },
    {
      "code": "XX",
      "flag": "🇽🇽",
      "count": 16
    }
  ]
}