{
  "generated_at": "2026-04-07T14:52:08.866871Z",
  "total": 340,
  "countries": [
    {
      "code": "RU",
      "flag": "🇷🇺",
      "count": 221
    },
    {
      "code": "BG",
      "flag": "🇧🇬",
      "count": 1
    },
    {
      "code": "CH",
      "flag": "🇨🇭",
      "count": 13
    },
    {
      "code": "CZ",
      "flag": "🇨🇿",
      "count": 3
    },
    {
      "code": "DE",
      "flag": "🇩🇪",
      "count": 23
    },
    {
      "code": "EE",
      "flag": "🇪🇪",
      "count": 1
    },
    {
      "code": "FI",
      "flag": "🇫🇮",
      "count": 5
    },
    {
      "code": "FR",
      "flag": "🇫🇷",
      "count": 11
    },
    {
      "code": "GB",
      "flag": "🇬🇧",
      "count": 1
    },
    {
      "code": "HU",
      "flag": "🇭🇺",
      "count": 3
    },
    {
      "code": "IT",
      "flag": "🇮🇹",
      "count": 1
    },
    {
      "code": "JP",
      "flag": "🇯🇵",
      "count": 1
    },
    {
      "code": "LT",
      "flag": "🇱🇹",
      "count": 2
    },
    {
      "code": "LV",
      "flag": "🇱🇻",
      "count": 2
    },
    {
      "code": "NL",
      "flag": "🇳🇱",
      "count": 13
    },
    {
      "code": "PH",
      "flag": "🇵🇭",
      "count": 1
    },
    {
      "code": "PL",
      "flag": "🇵🇱",
      "count": 3
    },
    {
      "code": "SE",
      "flag": "🇸🇪",
      "count": 19
    },
    {
      "code": "US",
      "flag": "🇺🇸",
      "count": 2
    },
    {
      "code": "XX",
      "flag": "🇽🇽",
      "count": 14
    }
  ]
}