{
  "generated_at": "2026-04-11T04:13:35.402693Z",
  "total": 502,
  "countries": [
    {
      "code": "RU",
      "flag": "🇷🇺",
      "count": 171
    },
    {
      "code": "AM",
      "flag": "🇦🇲",
      "count": 1
    },
    {
      "code": "CH",
      "flag": "🇨🇭",
      "count": 1
    },
    {
      "code": "CZ",
      "flag": "🇨🇿",
      "count": 3
    },
    {
      "code": "DE",
      "flag": "🇩🇪",
      "count": 166
    },
    {
      "code": "EE",
      "flag": "🇪🇪",
      "count": 5
    },
    {
      "code": "FI",
      "flag": "🇫🇮",
      "count": 10
    },
    {
      "code": "FR",
      "flag": "🇫🇷",
      "count": 2
    },
    {
      "code": "HU",
      "flag": "🇭🇺",
      "count": 51
    },
    {
      "code": "LT",
      "flag": "🇱🇹",
      "count": 38
    },
    {
      "code": "LV",
      "flag": "🇱🇻",
      "count": 2
    },
    {
      "code": "NL",
      "flag": "🇳🇱",
      "count": 12
    },
    {
      "code": "PL",
      "flag": "🇵🇱",
      "count": 3
    },
    {
      "code": "SE",
      "flag": "🇸🇪",
      "count": 3
    },
    {
      "code": "UN",
      "flag": "🇺🇳",
      "count": 2
    },
    {
      "code": "US",
      "flag": "🇺🇸",
      "count": 2
    },
    {
      "code": "XX",
      "flag": "🇽🇽",
      "count": 30
    }
  ]
}