{
  "generated_at": "2026-03-24T18:12:38.524618Z",
  "total": 1106,
  "countries": [
    {
      "code": "RU",
      "flag": "🇷🇺",
      "count": 467
    },
    {
      "code": "AL",
      "flag": "🇦🇱",
      "count": 6
    },
    {
      "code": "AT",
      "flag": "🇦🇹",
      "count": 2
    },
    {
      "code": "BR",
      "flag": "🇧🇷",
      "count": 2
    },
    {
      "code": "CA",
      "flag": "🇨🇦",
      "count": 3
    },
    {
      "code": "CH",
      "flag": "🇨🇭",
      "count": 1
    },
    {
      "code": "CN",
      "flag": "🇨🇳",
      "count": 9
    },
    {
      "code": "CY",
      "flag": "🇨🇾",
      "count": 8
    },
    {
      "code": "CZ",
      "flag": "🇨🇿",
      "count": 2
    },
    {
      "code": "DE",
      "flag": "🇩🇪",
      "count": 171
    },
    {
      "code": "EE",
      "flag": "🇪🇪",
      "count": 8
    },
    {
      "code": "ES",
      "flag": "🇪🇸",
      "count": 3
    },
    {
      "code": "FI",
      "flag": "🇫🇮",
      "count": 41
    },
    {
      "code": "FR",
      "flag": "🇫🇷",
      "count": 6
    },
    {
      "code": "GB",
      "flag": "🇬🇧",
      "count": 9
    },
    {
      "code": "GR",
      "flag": "🇬🇷",
      "count": 7
    },
    {
      "code": "HR",
      "flag": "🇭🇷",
      "count": 3
    },
    {
      "code": "HU",
      "flag": "🇭🇺",
      "count": 4
    },
    {
      "code": "IL",
      "flag": "🇮🇱",
      "count": 3
    },
    {
      "code": "IQ",
      "flag": "🇮🇶",
      "count": 2
    },
    {
      "code": "IT",
      "flag": "🇮🇹",
      "count": 3
    },
    {
      "code": "JP",
      "flag": "🇯🇵",
      "count": 17
    },
    {
      "code": "KR",
      "flag": "🇰🇷",
      "count": 12
    },
    {
      "code": "KZ",
      "flag": "🇰🇿",
      "count": 8
    },
    {
      "code": "LT",
      "flag": "🇱🇹",
      "count": 13
    },
    {
      "code": "LV",
      "flag": "🇱🇻",
      "count": 2
    },
    {
      "code": "MD",
      "flag": "🇲🇩",
      "count": 2
    },
    {
      "code": "NL",
      "flag": "🇳🇱",
      "count": 47
    },
    {
      "code": "NO",
      "flag": "🇳🇴",
      "count": 3
    },
    {
      "code": "PL",
      "flag": "🇵🇱",
      "count": 28
    },
    {
      "code": "RO",
      "flag": "🇷🇴",
      "count": 4
    },
    {
      "code": "RS",
      "flag": "🇷🇸",
      "count": 1
    },
    {
      "code": "SE",
      "flag": "🇸🇪",
      "count": 48
    },
    {
      "code": "SG",
      "flag": "🇸🇬",
      "count": 20
    },
    {
      "code": "TR",
      "flag": "🇹🇷",
      "count": 2
    },
    {
      "code": "US",
      "flag": "🇺🇸",
      "count": 73
    },
    {
      "code": "XX",
      "flag": "🇽🇽",
      "count": 66
    }
  ]
}