{
  "generated_at": "2026-03-27T13:55:10.898501Z",
  "total": 576,
  "countries": [
    {
      "code": "RU",
      "flag": "🇷🇺",
      "count": 313
    },
    {
      "code": "CA",
      "flag": "🇨🇦",
      "count": 3
    },
    {
      "code": "DE",
      "flag": "🇩🇪",
      "count": 66
    },
    {
      "code": "EE",
      "flag": "🇪🇪",
      "count": 5
    },
    {
      "code": "ES",
      "flag": "🇪🇸",
      "count": 18
    },
    {
      "code": "FI",
      "flag": "🇫🇮",
      "count": 12
    },
    {
      "code": "FR",
      "flag": "🇫🇷",
      "count": 1
    },
    {
      "code": "GB",
      "flag": "🇬🇧",
      "count": 5
    },
    {
      "code": "HU",
      "flag": "🇭🇺",
      "count": 18
    },
    {
      "code": "IT",
      "flag": "🇮🇹",
      "count": 18
    },
    {
      "code": "LT",
      "flag": "🇱🇹",
      "count": 8
    },
    {
      "code": "NL",
      "flag": "🇳🇱",
      "count": 22
    },
    {
      "code": "PL",
      "flag": "🇵🇱",
      "count": 18
    },
    {
      "code": "SE",
      "flag": "🇸🇪",
      "count": 4
    },
    {
      "code": "TR",
      "flag": "🇹🇷",
      "count": 1
    },
    {
      "code": "UN",
      "flag": "🇺🇳",
      "count": 4
    },
    {
      "code": "US",
      "flag": "🇺🇸",
      "count": 10
    },
    {
      "code": "XX",
      "flag": "🇽🇽",
      "count": 50
    }
  ]
}