{
  "generated_at": "2026-04-10T01:59:34.906584Z",
  "total": 475,
  "countries": [
    {
      "code": "RU",
      "flag": "🇷🇺",
      "count": 57
    },
    {
      "code": "AM",
      "flag": "🇦🇲",
      "count": 1
    },
    {
      "code": "CA",
      "flag": "🇨🇦",
      "count": 1
    },
    {
      "code": "CZ",
      "flag": "🇨🇿",
      "count": 4
    },
    {
      "code": "DE",
      "flag": "🇩🇪",
      "count": 158
    },
    {
      "code": "ES",
      "flag": "🇪🇸",
      "count": 2
    },
    {
      "code": "FI",
      "flag": "🇫🇮",
      "count": 7
    },
    {
      "code": "FR",
      "flag": "🇫🇷",
      "count": 6
    },
    {
      "code": "GB",
      "flag": "🇬🇧",
      "count": 3
    },
    {
      "code": "HK",
      "flag": "🇭🇰",
      "count": 1
    },
    {
      "code": "HU",
      "flag": "🇭🇺",
      "count": 103
    },
    {
      "code": "LT",
      "flag": "🇱🇹",
      "count": 40
    },
    {
      "code": "NL",
      "flag": "🇳🇱",
      "count": 32
    },
    {
      "code": "PL",
      "flag": "🇵🇱",
      "count": 15
    },
    {
      "code": "SE",
      "flag": "🇸🇪",
      "count": 5
    },
    {
      "code": "SK",
      "flag": "🇸🇰",
      "count": 1
    },
    {
      "code": "US",
      "flag": "🇺🇸",
      "count": 10
    },
    {
      "code": "XX",
      "flag": "🇽🇽",
      "count": 29
    }
  ]
}