{
  "generated_at": "2026-04-02T18:42:16.890557Z",
  "total": 330,
  "countries": [
    {
      "code": "RU",
      "flag": "🇷🇺",
      "count": 165
    },
    {
      "code": "CH",
      "flag": "🇨🇭",
      "count": 15
    },
    {
      "code": "DE",
      "flag": "🇩🇪",
      "count": 29
    },
    {
      "code": "EE",
      "flag": "🇪🇪",
      "count": 4
    },
    {
      "code": "ES",
      "flag": "🇪🇸",
      "count": 13
    },
    {
      "code": "FR",
      "flag": "🇫🇷",
      "count": 10
    },
    {
      "code": "GE",
      "flag": "🇬🇪",
      "count": 1
    },
    {
      "code": "HU",
      "flag": "🇭🇺",
      "count": 26
    },
    {
      "code": "ID",
      "flag": "🇮🇩",
      "count": 1
    },
    {
      "code": "LT",
      "flag": "🇱🇹",
      "count": 19
    },
    {
      "code": "NL",
      "flag": "🇳🇱",
      "count": 18
    },
    {
      "code": "PL",
      "flag": "🇵🇱",
      "count": 2
    },
    {
      "code": "SE",
      "flag": "🇸🇪",
      "count": 3
    },
    {
      "code": "UN",
      "flag": "🇺🇳",
      "count": 4
    },
    {
      "code": "US",
      "flag": "🇺🇸",
      "count": 5
    },
    {
      "code": "XX",
      "flag": "🇽🇽",
      "count": 15
    }
  ]
}