{
  "generated_at": "2026-03-25T09:16:50.872844Z",
  "total": 987,
  "countries": [
    {
      "code": "RU",
      "flag": "🇷🇺",
      "count": 317
    },
    {
      "code": "AL",
      "flag": "🇦🇱",
      "count": 15
    },
    {
      "code": "AT",
      "flag": "🇦🇹",
      "count": 2
    },
    {
      "code": "BR",
      "flag": "🇧🇷",
      "count": 1
    },
    {
      "code": "CA",
      "flag": "🇨🇦",
      "count": 2
    },
    {
      "code": "CH",
      "flag": "🇨🇭",
      "count": 6
    },
    {
      "code": "CY",
      "flag": "🇨🇾",
      "count": 1
    },
    {
      "code": "CZ",
      "flag": "🇨🇿",
      "count": 1
    },
    {
      "code": "DE",
      "flag": "🇩🇪",
      "count": 238
    },
    {
      "code": "EE",
      "flag": "🇪🇪",
      "count": 9
    },
    {
      "code": "ES",
      "flag": "🇪🇸",
      "count": 1
    },
    {
      "code": "FI",
      "flag": "🇫🇮",
      "count": 39
    },
    {
      "code": "FR",
      "flag": "🇫🇷",
      "count": 7
    },
    {
      "code": "GB",
      "flag": "🇬🇧",
      "count": 20
    },
    {
      "code": "HU",
      "flag": "🇭🇺",
      "count": 9
    },
    {
      "code": "JP",
      "flag": "🇯🇵",
      "count": 1
    },
    {
      "code": "KZ",
      "flag": "🇰🇿",
      "count": 1
    },
    {
      "code": "LT",
      "flag": "🇱🇹",
      "count": 1
    },
    {
      "code": "LV",
      "flag": "🇱🇻",
      "count": 2
    },
    {
      "code": "MD",
      "flag": "🇲🇩",
      "count": 11
    },
    {
      "code": "NL",
      "flag": "🇳🇱",
      "count": 55
    },
    {
      "code": "PL",
      "flag": "🇵🇱",
      "count": 41
    },
    {
      "code": "RO",
      "flag": "🇷🇴",
      "count": 6
    },
    {
      "code": "RS",
      "flag": "🇷🇸",
      "count": 3
    },
    {
      "code": "SE",
      "flag": "🇸🇪",
      "count": 51
    },
    {
      "code": "TR",
      "flag": "🇹🇷",
      "count": 1
    },
    {
      "code": "US",
      "flag": "🇺🇸",
      "count": 61
    },
    {
      "code": "XX",
      "flag": "🇽🇽",
      "count": 85
    }
  ]
}